augbondcurve/__init__.py
augbondcurve/model.py
dao2dao/__init__.py
dao2dao/proposal_inverter.py
dao2dao/test_broker.py
tokenengi/__init__.py
tokenengi/ltfswe.py
tokenengi/ltfte.py
tokenengi/qia.py
ltfte_library-0.0.9.dist-info/LICENSE
ltfte_library-0.0.9.dist-info/METADATA
ltfte_library-0.0.9.dist-info/WHEEL
ltfte_library-0.0.9.dist-info/top_level.txt
ltfte_library-0.0.9.dist-info/RECORD
